eview/__init__.py
eview-0.1.0.dist-info/METADATA
eview-0.1.0.dist-info/WHEEL
eview-0.1.0.dist-info/entry_points.txt
eview-0.1.0.dist-info/RECORD
