Metadata-Version: 2.4
Name: eview
Version: 0.1.0
Summary: Preview various kinds of text files used to generate images.
Author-email: clifton.clark@gmail.com
Classifier: Programming Language :: Python :: 3 :: Only
Classifier: Programming Language :: Python :: 3.12
Classifier: Programming Language :: Python :: 3.13
Classifier: Programming Language :: Python :: 3.14
Requires-Python: >=3.12
Requires-Dist: textual-fspicker>=0.6.0
Requires-Dist: textual-image>=0.8.4
Requires-Dist: textual-imageview>=0.1.1
Requires-Dist: textual>=6.7
